web_search_mcp/__init__.py
web_search_mcp/cli.py
web_search_mcp/config.py
web_search_mcp/models.py
web_search_mcp/search_manager.py
web_search_mcp/server.py
web_search_mcp/providers/__init__.py
web_search_mcp/providers/base.py
web_search_mcp/providers/bing.py
web_search_mcp/providers/duckduckgo.py
web_search_mcp/providers/google.py
web_search_mcp/providers/searxng.py
web_search_mcp/providers/serper.py
web_search_mcp/providers/serply.py
web_search_mcp/providers/tavily.py
realtimex_web_search_mcp_server-0.1.0.dist-info/METADATA
realtimex_web_search_mcp_server-0.1.0.dist-info/WHEEL
realtimex_web_search_mcp_server-0.1.0.dist-info/entry_points.txt
realtimex_web_search_mcp_server-0.1.0.dist-info/RECORD
