Metadata-Version: 2.4
Name: realtimex-web-search-mcp-server
Version: 0.1.0
Summary: MCP server for web search operations - provides utility tools for performing web searches via APIs with multiple provider support
Project-URL: Homepage, https://github.com/realtimex/web-search-mcp-server
Project-URL: Documentation, https://github.com/realtimex/web-search-mcp-server#readme
Project-URL: Repository, https://github.com/realtimex/web-search-mcp-server
Project-URL: Issues, https://github.com/realtimex/web-search-mcp-server/issues
Author-email: RealTimeX <support@realtimex.com>
License: MIT
Keywords: bing,duckduckgo,google,mcp,search-api,serpapi,web-search
Classifier: Development Status :: 4 - Beta
Classifier: Intended Audience :: Developers
Classifier: License :: OSI Approved :: MIT License
Classifier: Programming Language :: Python :: 3
Classifier: Programming Language :: Python :: 3.11
Classifier: Programming Language :: Python :: 3.12
Classifier: Topic :: Internet :: WWW/HTTP :: Indexing/Search
Classifier: Topic :: Software Development :: Libraries :: Python Modules
Classifier: Topic :: System :: Networking
Requires-Python: >=3.11
Requires-Dist: anyio>=4.0.0
Requires-Dist: beautifulsoup4>=4.12.0
Requires-Dist: click>=8.0.0
Requires-Dist: httpx>=0.25.0
Requires-Dist: lxml>=4.9.0
Requires-Dist: mcp[cli]>=1.2.0
Requires-Dist: pydantic>=2.0.0
Requires-Dist: structlog>=23.0.0
Provides-Extra: dev
Requires-Dist: black>=23.0.0; extra == 'dev'
Requires-Dist: mypy>=1.5.0; extra == 'dev'
Requires-Dist: pre-commit>=3.0.0; extra == 'dev'
Requires-Dist: pytest-asyncio>=0.21.0; extra == 'dev'
Requires-Dist: pytest-httpx>=0.21.0; extra == 'dev'
Requires-Dist: pytest-mock>=3.12.0; extra == 'dev'
Requires-Dist: pytest>=7.0.0; extra == 'dev'
Requires-Dist: ruff>=0.1.0; extra == 'dev'
